{
	"ide_version":"V1.6_20190123",
	"frameworks_checked":{
		"app":[],
		"iboot":[]
	},
	"libs_checked":{
		"app":[],
		"iboot":[]
	},
	"hardware":{
		"core":"cortex-m4",
		"cpu":"M487JIDAE",
		"board":"NuvotonM487"
	},
	"components_checked":{
		"app":[],
		"iboot":["black box",
		"ring buffer and line buffer",
		"debug information",
		"flash",
		"uart device file",
		"device file system",
		"device file system",
		"multiplex",
		"shell",
		"stdio",
		"kernel",
		"heap",
		"int",
		"lock",
		"message queue",
		"kernel object system",
		"memory pool",
		"time",
		"board config",
		"loader",
		"Nuvoton M480",
		"lib C",
		"cpu onchip dma",
		"cpu peri uart"]
	}
}